Metadata-Version: 2.1
Name: aiida-castep
Version: 2.0.1
Summary: AiiDA plugin for CASTEP
Home-page: https://github.com/zhubonan/aiida-castep
Author: Bonan Zhu
Author-email: zhubonan@outlook.com
License: MIT License
Platform: UNKNOWN
Classifier: Programming Language :: Python :: 3.8
Classifier: Programming Language :: Python :: 3.9
Classifier: Programming Language :: Python :: 3.10
Classifier: Framework :: AiiDA
Requires-Dist: aiida-core (~=2.0)
Requires-Dist: deepdiff
Requires-Dist: ase (<4.0,>=3.0)
Requires-Dist: matplotlib
Requires-Dist: six (<2.0,>=1.0)
Requires-Dist: click
Requires-Dist: castepinput (==0.1.6)
Requires-Dist: seekpath (~=1.9.3)
Requires-Dist: castepxbin (~=0.2.0)
Provides-Extra: docs
Requires-Dist: sphinx ; extra == 'docs'
Requires-Dist: sphinxcontrib-contentui ; extra == 'docs'
Requires-Dist: sphinxcontrib-details-directive ; extra == 'docs'
Requires-Dist: furo ; extra == 'docs'
Requires-Dist: markupsafe (<2.1) ; extra == 'docs'
Provides-Extra: pre-commit
Requires-Dist: pre-commit (==1.18.3) ; extra == 'pre-commit'
Requires-Dist: yapf (==0.28.0) ; extra == 'pre-commit'
Requires-Dist: prospector (==1.2.0) ; extra == 'pre-commit'
Requires-Dist: pylint-pytest ; extra == 'pre-commit'
Requires-Dist: pylint (==2.4.4) ; (python_version >= "3.0") and extra == 'pre-commit'
Provides-Extra: testing
Requires-Dist: pytest ; extra == 'testing'
Requires-Dist: pgtest (>=1.3.1,~=1.3) ; extra == 'testing'
Requires-Dist: pytest-cov ; extra == 'testing'
Requires-Dist: aiida-pseudo ; extra == 'testing'
